{
    "id": "dotnet",
    "version": "1.1.0",
    "name": "C# (.NET)",
    "description": "Develop C# and .NET based applications. Includes all needed SDKs, extensions, and dependencies.",
    "documentationURL": "https://github.com/devcontainers/templates/tree/main/src/dotnet",
    "publisher": "Dev Container Spec Maintainers",
    "licenseURL": "https://github.com/devcontainers/templates/blob/main/LICENSE",
    "options": {
        "imageVariant": {
            "type": "string",
            "description": ".NET version:",
            "proposals": [
                "7.0",
                "6.0",
                "3.1",
                "7.0-bullseye",
                "6.0-bullseye",
                "3.1-bullseye",
                "7.0-jammy",
                "6.0-jammy",
                "6.0-focal",
                "3.1-focal"
            ],
            "default": "7.0"
        },
        "nodeVersion": {
            "type": "string",
            "description": "Node.js version:",
            "proposals": [
                "none",
                "lts",
                "latest",
                "18",
                "16",
                "14"
            ],
            "default": "lts"
        }
    },
    "platforms": [
        ".NET",
        ".NET Core",
        "C#"
    ]
}