{
    "id": "javascript-node-postgres",
    "version": "1.1.0",
    "name": "Node.js & PostgreSQL",
    "description": "Develop applications in Node.js and PostgreSQL. Includes Node.js, eslint, and yarn in a container linked to a Postgres DB container",
    "documentationURL": "https://github.com/devcontainers/templates/tree/main/src/javascript-node-postgres",
    "publisher": "Dev Container Spec Maintainers",
    "licenseURL": "https://github.com/devcontainers/templates/blob/main/LICENSE",
    "options": {
        "imageVariant": {
            "type": "string",
            "description": "Node.js version (use -bullseye variants on local arm64/Apple Silicon):",
            "proposals": [
                "18",
                "16",
                "14",
                "18-bullseye",
                "16-bullseye",
                "14-bullseye",
                "18-buster",
                "16-buster",
                "14-buster"
            ],
            "default": "18"
        }
    },
    "platforms": [
        "Node.js",
        "JavaScript",
        "PostgreSQL DB"
    ]
}
