{
    "id": "go",
    "version": "6.0.0",
    "name": "Go",
    "description": "Develop Go based applications. Includes appropriate runtime args, Go, common tools, extensions, and dependencies.",
    "documentationURL": "https://github.com/devcontainers/templates/tree/main/src/go",
    "publisher": "Dev Container Spec Maintainers",
    "licenseURL": "https://github.com/devcontainers/templates/blob/main/LICENSE",
    "options": {
        "imageVariant": {
            "type": "string",
            "description": "Go version:",
            "proposals": [
				"1.26-trixie",
				"1.25-trixie",
				"1.26-bookworm",
                "1.25-bookworm"
            ],
            "default": "1.26-trixie"
        }
    },
    "platforms": ["Go"],
    "optionalPaths": [
        ".github/*"
    ]
}
